qcentroid_runtime_qiskit/__init__.py
qcentroid_runtime_qiskit/providers/AQT.py
qcentroid_runtime_qiskit/providers/AliceBob.py
qcentroid_runtime_qiskit/providers/IBMCloud.py
qcentroid_runtime_qiskit/providers/IBMQuantum.py
qcentroid_runtime_qiskit/providers/IQM.py
qcentroid_runtime_qiskit/providers/IonQ.py
qcentroid_runtime_qiskit/providers/QCtrl.py
qcentroid_runtime_qiskit/providers/QCtrlEmbedded.py
qcentroid_runtime_qiskit/providers/QiskitAbstractProvider.py
qcentroid_runtime_qiskit/providers/QiskitRuntimeAbstractProvider.py
qcentroid_runtime_qiskit/providers/Quantinuum.py
qcentroid_runtime_qiskit/providers/Qulacs.py
qcentroid_runtime_qiskit/providers/Rigetti.py
qcentroid_runtime_qiskit/providers/__init__.py
qcentroid_runtime_qiskit-0.1.4.dist-info/LICENSE
qcentroid_runtime_qiskit-0.1.4.dist-info/METADATA
qcentroid_runtime_qiskit-0.1.4.dist-info/WHEEL
qcentroid_runtime_qiskit-0.1.4.dist-info/RECORD
