Metadata-Version: 2.1
Name: qcentroid-runtime-qiskit
Version: 0.1.4
Summary: Library to interact with qcentroid qiskit runtime
Home-page: https://www.qcentroid.xyz
License: MIT
Author: QCentroid
Author-email: info@qcentroid.xyz
Requires-Python: >=3.8,<4.0
Classifier: License :: OSI Approved :: MIT License
Classifier: Operating System :: OS Independent
Classifier: Programming Language :: Python :: 3
Classifier: Programming Language :: Python :: 3.8
Classifier: Programming Language :: Python :: 3.9
Classifier: Programming Language :: Python :: 3.10
Classifier: Programming Language :: Python :: 3.11
Classifier: Programming Language :: Python :: 3.12
Provides-Extra: test
Requires-Dist: pytest (>=7.4,<7.5) ; extra == "test"
Requires-Dist: qiskit-ibm-runtime (>=0.23,<1.0)
Project-URL: Documentation, https://github.com/QCentroid/qcentroid-runtime-qiskit
Project-URL: Repository, https://github.com/QCentroid/qcentroid-runtime-qiskit
